fundcrunch/__init__.py
fundcrunch/drivers/__init__.py
fundcrunch/drivers/binance.py
fundcrunch/drivers/binancews.py
fundcrunch/drivers/binancews_private.py
fundcrunch/drivers/bitfinex.py
fundcrunch/drivers/bittrex.py
fundcrunch/drivers/ccxtdriver.py
fundcrunch/drivers/coinmarketcup.py
fundcrunch/drivers/exchdriver.py
fundcrunch/drivers/hitbtc.py
fundcrunch/drivers/kraken.py
fundcrunch/drivers/kucoin.py
fundcrunch/drivers/latoken.py
fundcrunch/drivers/latokenws.py
fundcrunch/drivers/liqui.py
fundcrunch/utils/__init__.py
fundcrunch/utils/endpoint.py
fundcrunch/utils/endpoint_binder.py
fundcrunch/utils/history.py
fundcrunch-0.1.1.dist-info/LICENSE
fundcrunch-0.1.1.dist-info/METADATA
fundcrunch-0.1.1.dist-info/WHEEL
fundcrunch-0.1.1.dist-info/top_level.txt
fundcrunch-0.1.1.dist-info/RECORD
