Metadata-Version: 2.1
Name: fundcrunch
Version: 0.1.1
Summary: The Fundcrunch.Tech library for market data processing in real time or on history.
Home-page: https://github.com/fundcrunch-tech/fundcrunch_py
Author: Sergey Bryukov
Author-email: hello@fundcrunch.tech
License: MIT
Platform: UNKNOWN
Classifier: Programming Language :: Python :: 3
Classifier: License :: OSI Approved :: MIT License
Classifier: Operating System :: OS Independent
Requires-Python: >=3.7
Requires-Dist: requests
Requires-Dist: websockets
Requires-Dist: ccxt
Requires-Dist: pyzmq
Requires-Dist: pandas
